CHANGES.txt
LICENSE
MANIFEST.in
README.rst
requirements.txt
setup.py
firapria/__init__.py
firapria/cli.py
firapria/pollution.py
firapria.egg-info/PKG-INFO
firapria.egg-info/SOURCES.txt
firapria.egg-info/dependency_links.txt
firapria.egg-info/entry_points.txt
firapria.egg-info/requires.txt
firapria.egg-info/top_level.txt