Metadata-Version: 1.1
Name: firapria
Version: 0.1.1
Summary: Get pollution indices for IDF (France)
Home-page: https://github.com/bfontaine/firapria
Author: Baptiste Fontaine
Author-email: b@ptistefontaine.fr
License: Copyright © 2014 – Baptiste Fontaine
